Metadata-Version: 1.1
Name: mdmail
Version: 0.1.3
Summary: Send email written in Markdown
Home-page: https://github.com/yejianye/mdmail
Author: Jianye Ye
Author-email: yejianye@gmail.com
License: Copyright (c) 2017, Jianye Ye
